MANIFEST.in
setup.cfg
setup.py
unlocker/__init__.py
unlocker/__main__.py
unlocker/authority.py
unlocker/bootstrap.py
unlocker/database.py
unlocker/display.py
unlocker/keychain.py
unlocker/manager.py
unlocker/migrate.py
unlocker/stream.py
unlocker.egg-info/PKG-INFO
unlocker.egg-info/SOURCES.txt
unlocker.egg-info/dependency_links.txt
unlocker.egg-info/entry_points.txt
unlocker.egg-info/requires.txt
unlocker.egg-info/top_level.txt
unlocker/data/__init__.py
unlocker/data/shell/lock.sh
unlocker/data/shell/unlock.sh
unlocker/util/__init__.py
unlocker/util/helper.py
unlocker/util/log.py
unlocker/util/passkey.py
unlocker/util/secret.py
unlocker/util/service.py
unlocker/util/shell.py